{
  "Url": "http://www.baomoi.com/De-xuat-don-bo-hon-8000-ha-cam-sanh-nhiem-benh/82/13476760.epi",
  "Time": "04/04/2014 03:08",
  "Title": "Đề xuất đốn bỏ hơn 8.000 ha cam sành nhiễm bệnh",
  "Category": "Tin tức > Sức khỏe",
  "Description": "Hiện Hậu Giang có khoảng 1.300 ha cam sành bị nhiễm bệnh (chiếm 20% tổng diện tích), chủ yếu ở những cây sắp cho trái hoặc cho trái một mùa nhưng vàng lá, héo dần, làm giảm chất lượng trái và chết.",
  "Content": "<tr><td><table width='100%'> <tr> <td> </td> </tr> <tr> <td> </td> </tr> </table> <div> <p>Theo các chuyên gia nông nghiệp, nguyên nhân bệnh tấn công, khó phòng trị là do người dân trồng theo phong trào, không đúng kỹ thuật; lên liếp, đắp mô quá cao so với mặt nước; mua cây giống không sạch bệnh. Hiện bệnh này không có thuốc đặc trị, tiêu hủy và làm sạch nền đất là cách phòng bệnh hữu hiệu nhất. </p> <p>Giám đốc Sở NN-PTNT Hậu Giang Nguyễn Văn Đồng cho biết hiện dịch bệnh trên cam sành tiếp tục lây lan trên diện rộng. Do đó, ngành đang xin chủ trương từ UBND tỉnh để công bố dịch và có mức hỗ trợ cho người dân đốn bỏ khoảng 8.000 ha cam sành đồng thời ban hành quy trình trồng cam sành an toàn để phục hồi vườn cam.</p> <p><strong>Kim Anh </strong></p> </div><br /></td></tr>",
  "KeyWords": [
    "cam sành",
    "Hậu Giang",
    "nhiễm bệnh",
    "vàng lá",
    "thuốc đặc trị",
    "Sở Nông Nghiệp Và Phát Triển Nông Thôn",
    "nền đất",
    "tiêu hủy",
    "trên diện rộng",
    "phòng bệnh",
    "mặt nước"
  ],
  "Trends": [
    {
      "word": "Bảo Bình",
      "weith": "3"
    },
    {
      "word": "Bệnh viện Nhi TW",
      "weith": "2"
    },
    {
      "word": "Bộ Y Tế",
      "weith": "2"
    },
    {
      "word": "Ca-lo",
      "weith": "3"
    },
    {
      "word": "cơ thể",
      "weith": "6"
    },
    {
      "word": "Cự Giải",
      "weith": "5"
    },
    {
      "word": "Facebook",
      "weith": "2"
    },
    {
      "word": "kết hôn",
      "weith": "6"
    },
    {
      "word": "khóc",
      "weith": "4"
    },
    {
      "word": "khối u",
      "weith": "4"
    },
    {
      "word": "làn da",
      "weith": "1"
    },
    {
      "word": "ly hôn",
      "weith": "3"
    },
    {
      "word": "mang thai",
      "weith": "4"
    },
    {
      "word": "mặt nạ",
      "weith": "4"
    },
    {
      "word": "minh họa",
      "weith": "5"
    },
    {
      "word": "ngoại tình",
      "weith": "6"
    },
    {
      "word": "quan hệ tình dục",
      "weith": "5"
    },
    {
      "word": "Sở Y Tế",
      "weith": "5"
    },
    {
      "word": "Song Ngư",
      "weith": "2"
    },
    {
      "word": "Sư Tử",
      "weith": "3"
    },
    {
      "word": "Thiên Bình",
      "weith": "5"
    },
    {
      "word": "tử cung",
      "weith": "4"
    },
    {
      "word": "tự thiêu",
      "weith": "6"
    },
    {
      "word": "Tuấn Hưng",
      "weith": "2"
    },
    {
      "word": "ung thư",
      "weith": "1"
    },
    {
      "word": "Vacxin",
      "weith": "1"
    },
    {
      "word": "vi khuẩn",
      "weith": "6"
    },
    {
      "word": "virus",
      "weith": "1"
    },
    {
      "word": "Vitamin C",
      "weith": "5"
    },
    {
      "word": "yêu",
      "weith": "1"
    }
  ]
}