{
  "topic": "the-gioi",
  "time": "2025-10-24T15:19:00.000Z",
  "title": "Quan chức cấp cao Nga-Mỹ họp bàn tại Miami vào ngày 25/10",
  "url": "https://baomoi.com/quan-chuc-cap-cao-nga-my-hop-ban-tai-miami-vao-ngay-25-10-c53577730.epi",
  "content": "\u003cdiv class\u003d\"content-main relative\"\u003e\n \u003ch1 class\u003d\"block text-[4rem] text-[var(--dark)] leading-[4.4rem] font-semibold mb-[5px]\"\u003eQuan chức cấp cao Nga-Mỹ họp b\u0026agrave;n tại Miami v\u0026agrave;o ng\u0026agrave;y 25/10\u003c/h1\u003e\n \u003cdiv class\u003d\"content-meta flex items-center flex-wrap flex-row text-[1.3rem] leading-[2rem] font-normal text-[#999] truncate h-[30px] mb-[10px] [\u0026amp;\u0026gt;:not(:first-child)]:ml-[25px]\"\u003e\n  \u003cdiv class\u003d\"flex items-center\"\u003e\n   \u003ca href\u003d\"/bao-vietnamplus-vietnamplus-p293.epi\" class\u003d\"bm-card-source flex items-center shrink-0\" title\u003d\"B\u0026aacute;o VietnamPlus\"\u003e\n    \u003cfigure class\u003d\"image opacity-80 w-auto h-[16px]\" style\u003d\"width:81.25px;height:20px\" aria-label\u003d\"Logo nh\u0026agrave; xuất bản\"\u003e\n     \u003cpicture\u003e\n      \u003csource srcset\u003d\"https://photo-baomoi.bmcdn.me/d1c2f8ad25eeccb095ff.png\" type\u003d\"image/avif\"\u003e\u003c/source\u003e\n      \u003csource srcset\u003d\"https://photo-baomoi.bmcdn.me/d1c2f8ad25eeccb095ff.png\" type\u003d\"image/webp\"\u003e\u003c/source\u003e\n      \u003cimg src\u003d\"https://photo-baomoi.bmcdn.me/d1c2f8ad25eeccb095ff.png\" alt\u003d\"B\u0026aacute;o VietnamPlus\" width\u003d\"260\" height\u003d\"64\" /\u003e\n     \u003c/picture\u003e\n    \u003c/figure\u003e\u003c/a\u003e\n   \u003cspan\u003e\u003cbutton class\u003d\"relative text-[14px] leading-[normal] font-normal text-center cursor-pointer normal-case border-0 transition-button disabled:shadow-none disabled:opacity-50 disabled:cursor-not-allowed follow-button flex items-center item-star ml-[10px]\" tabindex\u003d\"0\" type\u003d\"button\" title\u003d\"Theo d\u0026otilde;i \u0026quot;VietnamPlus\u0026quot;\" aria-label\u003d\"Button\"\u003e\u003ci class\u003d\"icon inline-block font-[\u0027bm-font-icon\u0027] not-italic font-normal normal-case leading-none antialiased [speak:never] [font-variant:normal] ic-star text-[var(--primary)]\"\u003e\u003c/i\u003e\u003c/button\u003e\u003c/span\u003e\n  \u003c/div\u003e\n  \u003ctime datetime\u003d\"2025-10-24T15:19:00.000Z\"\u003e24/10/2025\u003c/time\u003e\n  \u003ca href\u003d\"/quan-chuc-cap-cao-nga-my-hop-ban-tai-miami-vao-ngay-25-10-rp53577730.epi\" class\u003d\"\"\u003e\u003cspan\u003e4\n    \u003c!-- --\u003e đăng lại\u003c/span\u003e\u003c/a\u003e\n  \u003ca href\u003d\"/vladimir-putin-t31528056.epi\" class\u003d\"related inline !text-[#adb5bd] hover:!text-[var(--primary)]\"\u003e2119\n   \u003c!-- --\u003e li\u0026ecirc;n quan\u003c/a\u003e\n  \u003ca href\u003d\"/quan-chuc-cap-cao-nga-my-hop-ban-tai-miami-vao-ngay-25-10-r53577730.epi\" class\u003d\"origin item-origin\" target\u003d\"_blank\" rel\u003d\"noopener noreferrer\"\u003e\u003ci class\u003d\"icon inline-block font-[\u0027bm-font-icon\u0027] not-italic font-normal normal-case antialiased [speak:never] [font-variant:normal] ic-copy text-[13px] mr-[5px]\"\u003e\u003c/i\u003e\u003cspan\u003eGốc\u003c/span\u003e\u003c/a\u003e\n \u003c/div\u003e\n \u003ch3 class\u003d\"sapo block text-[2rem] leading-[2.6rem] font-semibold text-[var(--dark)] p-[10px] bg-[#f2f4f5]\"\u003eĐặc ph\u0026aacute;i vi\u0026ecirc;n của Tổng thống Nga Vladimir Putin, \u0026ocirc;ng Kirill Dmitriev, đang c\u0026oacute; mặt tại Mỹ để gặp c\u0026aacute;c quan chức trong ch\u0026iacute;nh quyền Tổng thống Donald Trump, trong đ\u0026oacute; c\u0026oacute; đặc ph\u0026aacute;i vi\u0026ecirc;n Steve Witkoff.\u003c/h3\u003e\n \u003cdiv class\u003d\"content-body text-[2rem] leading-[2.6rem] text-black mt-[15px] break-words overflow-hidden [\u0026amp;_h1]:mb-[15px] [\u0026amp;_h2]:mb-[15px] [\u0026amp;_h3]:mb-[15px] [\u0026amp;_h4]:mb-[15px] [\u0026amp;_h5]:mb-[15px] [\u0026amp;_p]:mb-[15px] [\u0026amp;\u0026gt;div]:mb-[15px]\"\u003e\n  \u003cdiv class\u003d\"image-wrapper relative z-[1] body-image after:absolute after:top-0 after:left-0 after:z-[-1] after:w-full after:h-full after:opacity-40 after:bg-[url(\u0027https://baomoi-static.bmcdn.me/web/styles/img/logo-baomoi-gray.png\u0027)] after:bg-[length:20%_auto] after:bg-[position:center_50%] after:bg-no-repeat after:bg-[#e9ecef]\"\u003e\n   \u003ci class\u003d\"icon font-[\u0027bm-font-icon\u0027] not-italic font-normal normal-case leading-none antialiased [speak:never] [font-variant:normal] ic-search-plus w-[44px] h-[44px] flex items-center justify-center absolute right-[5px] top-[5px] z-[2] text-white rounded-full cursor-pointer bg-[rgba(0,0,0,0.5)] hover:bg-[var(--primary)]\"\u003e\u003c/i\u003e\n   \u003cbutton class\u003d\"image lazy-image overflow-hidden photo block leading-[0] cursor-pointer text-center opacity-0\" style\u003d\"width:625px;height:425px\"\u003e\n    \u003cpicture\u003e\n     \u003csource srcset\u003d\"data:image/gif;base64,R0lGODlhAQABAIAAAP///wAAACH5BAEAAAAALAAAAAABAAEAAAICRAEAOw\u003d\u003d\" type\u003d\"image/avif\"\u003e\u003c/source\u003e\n     \u003csource srcset\u003d\"data:image/gif;base64,R0lGODlhAQABAIAAAP///wAAACH5BAEAAAAALAAAAAABAAEAAAICRAEAOw\u003d\u003d\" type\u003d\"image/webp\"\u003e\u003c/source\u003e\n     \u003cimg src\u003d\"data:image/gif;base64,R0lGODlhAQABAIAAAP///wAAACH5BAEAAAAALAAAAAABAAEAAAICRAEAOw\u003d\u003d\" alt\u003d\"Đặc ph\u0026aacute;i vi\u0026ecirc;n của Tổng thống Nga Vladimir Putin, \u0026ocirc;ng Kirill Dmitriev. (Nguồn: AFP/Getty Images)\" width\u003d\"625\" height\u003d\"425\" /\u003e\n    \u003c/picture\u003e\u003c/button\u003e\n  \u003c/div\u003e\n  \u003cp class\u003d\"text media-caption text-center text-[18px] leading-[24px]\"\u003e\u003cem\u003eĐặc ph\u0026aacute;i vi\u0026ecirc;n của Tổng thống Nga Vladimir Putin, \u0026ocirc;ng Kirill Dmitriev. (Nguồn: AFP/Getty Images)\u003c/em\u003e\u003c/p\u003e\n  \u003cp class\u003d\"text\"\u003eReuters đưa tin theo c\u0026aacute;c h\u0026atilde;ng truyền th\u0026ocirc;ng \u003ca class\u003d\"tag-link\" href\u003d\"/my-tag81.epi\"\u003eMỹ\u003c/a\u003e, đặc ph\u0026aacute;i vi\u0026ecirc;n của Tổng thống Nga Vladimir Putin, \u0026ocirc;ng Kirill Dmitriev, đang c\u0026oacute; mặt tại Mỹ để gặp c\u0026aacute;c quan chức trong ch\u0026iacute;nh quyền Tổng thống Donald Trump, trong đ\u0026oacute; c\u0026oacute; đặc ph\u0026aacute;i vi\u0026ecirc;n Steve Witkoff.\u003c/p\u003e\n  \u003cp class\u003d\"text\"\u003eTrang Axios tiết lộ cuộc gặp giữa \u0026ocirc;ng Dmitriev v\u0026agrave; \u0026ocirc;ng Witkoff dự kiến diễn ra tại Miami v\u0026agrave;o ng\u0026agrave;y 25/10.\u003c/p\u003e\n  \u003cp class\u003d\"text\"\u003eCNN dẫn c\u0026aacute;c nguồn thạo tin cho hay \u0026ocirc;ng Dmitriev được kỳ vọng sẽ gặp c\u0026aacute;c quan chức ch\u0026iacute;nh quyền Mỹ “nhằm tiếp tục c\u0026aacute;c cuộc thảo luận về quan hệ Mỹ-Nga.”\u003c/p\u003e\n  \u003cp class\u003d\"text\"\u003eTrong tuần n\u0026agrave;y, Tổng thống \u003ca class\u003d\"tag-link\" href\u003d\"/donald-trump-tag673.epi\"\u003eTrump\u003c/a\u003e đ\u0026atilde; \u0026aacute;p đặt c\u0026aacute;c biện ph\u0026aacute;p trừng phạt đối với hai tập đo\u0026agrave;n dầu kh\u0026iacute; lớn nhất của Nga nhằm g\u0026acirc;y sức \u0026eacute;p buộc Moskva chấm dứt chiến sự tại Ukraine.\u003c/p\u003e\n  \u003cp class\u003d\"text\"\u003eSau đ\u0026oacute;, Tổng thống \u003ca class\u003d\"tag-link\" href\u003d\"/lien-bang-nga-tag117.epi\"\u003eNga\u003c/a\u003e Vladimir Putin đ\u0026atilde; cảnh b\u0026aacute;o về những hậu quả nghi\u0026ecirc;m trọng nếu Mỹ tiếp tục \u0026aacute;p đặt c\u0026aacute;c biện ph\u0026aacute;p trừng phạt nhằm v\u0026agrave;o ng\u0026agrave;nh dầu mỏ Nga.\u003c/p\u003e\n  \u003cp class\u003d\"text\"\u003eTrong cuộc gặp gỡ với c\u0026aacute;c nh\u0026agrave; b\u0026aacute;o, \u0026ocirc;ng \u003ca class\u003d\"tag-link\" href\u003d\"/vladimir-putin-tag87.epi\"\u003ePutin\u003c/a\u003e tiết lộ đ\u0026atilde; thảo luận với Tổng thống Donald Trump về vị thế của dầu mỏ Nga tr\u0026ecirc;n thị trường to\u0026agrave;n cầu.\u003c/p\u003e\n  \u003cp class\u003d\"text\"\u003eNh\u0026agrave; l\u0026atilde;nh đạo Nga nhận định rằng những cố vấn đang th\u0026uacute;c đẩy ch\u0026iacute;nh quyền Mỹ \u0026aacute;p đặt lệnh trừng phạt đối với ng\u0026agrave;nh dầu mỏ Nga thực chất đang h\u0026agrave;nh động chống lại lợi \u0026iacute;ch của ch\u0026iacute;nh nước Mỹ.\u003c/p\u003e\n  \u003cp class\u003d\"text\"\u003e\u0026Ocirc;ng cảnh b\u0026aacute;o nếu nguồn cung dầu mỏ v\u0026agrave; c\u0026aacute;c sản phẩm dầu mỏ của Nga tr\u0026ecirc;n thị trường \u003ca class\u003d\"tag-link\" href\u003d\"/the-gioi.epi\"\u003ethế giới\u003c/a\u003e giảm mạnh, điều n\u0026agrave;y sẽ dẫn đến sự gia tăng đ\u0026aacute;ng kể về gi\u0026aacute; dầu v\u0026agrave; c\u0026aacute;c sản phẩm dầu mỏ tr\u0026ecirc;n to\u0026agrave;n cầu, bao gồm cả tại c\u0026aacute;c trạm xăng ở Mỹ.\u003c/p\u003e\n  \u003cp class\u003d\"text\"\u003e\u0026Ocirc;ng Putin cũng nhấn mạnh rằng x\u0026eacute;t đến \u0026quot;lịch tr\u0026igrave;nh ch\u0026iacute;nh trị nội bộ\u0026quot; của Mỹ, một số tiến tr\u0026igrave;nh sẽ rất nhạy cảm trong vấn đề n\u0026agrave;y. \u0026Ocirc;ng đặt c\u0026acirc;u hỏi về động cơ của những người đang th\u0026uacute;c đẩy ch\u0026iacute;nh quyền Mỹ đưa ra c\u0026aacute;c quyết định trừng phạt, ngụ \u0026yacute; rằng họ c\u0026oacute; thể kh\u0026ocirc;ng thực sự phục vụ lợi \u0026iacute;ch quốc gia của Mỹ.\u003c/p\u003e\n  \u003cp class\u003d\"text\"\u003eNngười ph\u0026aacute;t ng\u0026ocirc;n Bộ Ngoại giao Nga Maria Zakharova cũng đ\u0026atilde; l\u0026ecirc;n \u0026aacute;n c\u0026aacute;c biện ph\u0026aacute;p trừng phạt mới l\u0026agrave; h\u0026agrave;nh động \u0026quot;ho\u0026agrave;n to\u0026agrave;n phản t\u0026aacute;c dụng,\u0026quot; đồng thời khẳng định Nga đ\u0026atilde; \u0026quot;miễn dịch với trừng phạt phương T\u0026acirc;y.\u0026quot;\u003c/p\u003e\n  \u003cp class\u003d\"text\"\u003eC\u0026ograve;n cựu Tổng thống Nga Dmitry Medvedev c\u0026oacute; phản ứng gay gắt hơn khi gọi đ\u0026acirc;y l\u0026agrave; \u0026quot;h\u0026agrave;nh động chiến tranh\u0026quot; v\u0026agrave; c\u0026aacute;o buộc \u0026ocirc;ng Trump \u0026quot;đ\u0026atilde; đứng hẳn về ph\u0026iacute;a ch\u0026acirc;u \u0026Acirc;u.\u0026quot;\u003c/p\u003e\n  \u003cp class\u003d\"text\"\u003eTrong khi đ\u0026oacute;, ng\u0026agrave;y 23/10, Ủy ban Đối ngoại Thượng viện Mỹ đ\u0026atilde; th\u0026ocirc;ng qua c\u0026aacute;c dự luật nhằm liệt Nga l\u0026agrave; quốc gia t\u0026agrave;i trợ khủng bố, cải thiện quy tr\u0026igrave;nh tịch thu t\u0026agrave;i sản của Nga bị phong tỏa để hỗ trợ \u003ca class\u003d\"tag-link\" href\u003d\"/ukraine-tag88.epi\"\u003eUkraine\u003c/a\u003e, v\u0026agrave; \u0026aacute;p đặt trừng phạt đối với c\u0026aacute;c c\u0026ocirc;ng ty Trung Quốc bị c\u0026aacute;o buộc ủng hộ qu\u0026acirc;n đội Nga..\u003c/p\u003e\n  \u003cp class\u003d\"text\"\u003eĐến ng\u0026agrave;y 24/10, Người ph\u0026aacute;t ng\u0026ocirc;n Bộ Ngoại giao Nga Maria Zakharova cho rằng \u0026yacute; đồ của Mỹ nhằm liệt Nga v\u0026agrave;o danh s\u0026aacute;ch “nh\u0026agrave; t\u0026agrave;i trợ khủng bố” l\u0026agrave; nỗ lực ph\u0026aacute; hoại đối thoại giữa Moskva v\u0026agrave; Washington, bao gồm cả vấn đề đo\u0026agrave;n tụ c\u0026aacute;c gia đ\u0026igrave;nh.\u003c/p\u003e\n  \u003cp class\u003d\"text\"\u003eB\u0026agrave; Zakharova n\u0026ecirc;u r\u0026otilde;: “Ch\u0026uacute;ng t\u0026ocirc;i coi s\u0026aacute;ng kiến lập ph\u0026aacute;p n\u0026agrave;y l\u0026agrave; một nỗ lực nhằm ph\u0026aacute; hoại đối thoại đ\u0026atilde; được thiết lập giữa Nga v\u0026agrave; Mỹ, bao gồm cả về vấn đề đo\u0026agrave;n tụ c\u0026aacute;c trẻ em v\u0026igrave; nhiều l\u0026yacute; do kh\u0026aacute;c nhau đ\u0026atilde; mất li\u0026ecirc;n lạc với gia đ\u0026igrave;nh trong cuộc xung đột ở Ukraine.\u0026quot;\u003c/p\u003e\n  \u003cp class\u003d\"text\"\u003eHồi tuần trước, \u0026ocirc;ng Trump đ\u0026atilde; điện đ\u0026agrave;m với Tổng thống Putin v\u0026agrave; cho biết dự định sẽ sớm gặp nh\u0026agrave; l\u0026atilde;nh đạo Nga, song c\u0026aacute;c quan chức Mỹ n\u0026oacute;i rằng cuộc gặp hiện đang tạm ho\u0026atilde;n./.\u003c/p\u003e\n  \u003cp class\u003d\"text body-author text-right\"\u003e\u003cstrong\u003e(Vietnam+)\u003c/strong\u003e\u003c/p\u003e\n \u003c/div\u003e\n \u003cdiv class\u003d\"pswp\" tabindex\u003d\"-1\" role\u003d\"dialog\" aria-hidden\u003d\"true\"\u003e\n  \u003cdiv class\u003d\"pswp__bg\"\u003e\u003c/div\u003e\n  \u003cdiv class\u003d\"pswp__scroll-wrap\"\u003e\n   \u003cdiv class\u003d\"pswp__container\"\u003e\n    \u003cdiv class\u003d\"pswp__item\"\u003e\u003c/div\u003e\n    \u003cdiv class\u003d\"pswp__item\"\u003e\u003c/div\u003e\n    \u003cdiv class\u003d\"pswp__item\"\u003e\u003c/div\u003e\n   \u003c/div\u003e\n   \u003cdiv class\u003d\"pswp__ui pswp__ui--hidden\"\u003e\n    \u003cdiv class\u003d\"pswp__top-bar\"\u003e\n     \u003cdiv class\u003d\"pswp__counter\"\u003e\u003c/div\u003e\n     \u003cbutton type\u003d\"button\" class\u003d\"pswp__button pswp__button--close\" title\u003d\"Close (Esc)\"\u003e\u003c/button\u003e\n     \u003cbutton type\u003d\"button\" class\u003d\"pswp__button pswp__button--share\" title\u003d\"Share\"\u003e\u003c/button\u003e\n     \u003cbutton type\u003d\"button\" class\u003d\"pswp__button pswp__button--fs\" title\u003d\"Toggle fullscreen\"\u003e\u003c/button\u003e\n     \u003cbutton type\u003d\"button\" class\u003d\"pswp__button pswp__button--zoom\" title\u003d\"Zoom in/out\"\u003e\u003c/button\u003e\n     \u003cdiv class\u003d\"pswp__preloader\"\u003e\n      \u003cdiv class\u003d\"pswp__preloader__icn\"\u003e\n       \u003cdiv class\u003d\"pswp__preloader__cut\"\u003e\n        \u003cdiv class\u003d\"pswp__preloader__donut\"\u003e\u003c/div\u003e\n       \u003c/div\u003e\n      \u003c/div\u003e\n     \u003c/div\u003e\n    \u003c/div\u003e\n    \u003cdiv class\u003d\"pswp__share-modal pswp__share-modal--hidden pswp__single-tap\"\u003e\n     \u003cdiv class\u003d\"pswp__share-tooltip\"\u003e\u003c/div\u003e\n    \u003c/div\u003e\n    \u003cbutton type\u003d\"button\" class\u003d\"pswp__button pswp__button--arrow--left\" title\u003d\"Previous (arrow left)\"\u003e\u003c/button\u003e\n    \u003cbutton type\u003d\"button\" class\u003d\"pswp__button pswp__button--arrow--right\" title\u003d\"Next (arrow right)\"\u003e\u003c/button\u003e\n    \u003cdiv class\u003d\"pswp__caption\"\u003e\n     \u003cdiv class\u003d\"pswp__caption__center\"\u003e\u003c/div\u003e\n    \u003c/div\u003e\n   \u003c/div\u003e\n  \u003c/div\u003e\n \u003c/div\u003e\n \u003cdiv class\u003d\"content-social absolute top-[55px] w-[40px] h-full ml-[-75px]\"\u003e\n  \u003cdiv class\u003d\"content-social-container relative top-[unset] bottom-[unset] text-center w-[50px]\"\u003e\n   \u003cbutton class\u003d\"btn-social btn-facebook w-[40px] h-[40px] flex items-center justify-center text-[20px] mt-0 mb-[10px] rounded-[50%] bg-[#4e598f] hover:bg-[#3c446e]\" title\u003d\"Chia sẻ qua Facebook\"\u003e\u003ci class\u003d\"bm-icon inline-block bg-[url(https://baomoi-static.bmcdn.me/web/styles/img/bm-icon-2.0.3.png)] bg-[length:100px_4250px] align-middle w-[40px] h-[40px] bg-[0_-3400px] hover:bg-[-50px_-3400px]\"\u003e\u003c/i\u003e\u003c/button\u003e\n   \u003cspan\u003e\u003cbutton class\u003d\"relative font-normal text-center cursor-pointer normal-case border-0 transition-button disabled:shadow-none disabled:opacity-50 disabled:cursor-not-allowed item-like hover:text-[var(--primary)] btn-social w-[40px] h-[40px] flex items-center justify-center text-[20px] mt-0 mb-[10px] rounded-[50%] bg-[#e9ecef]\" tabindex\u003d\"0\" type\u003d\"button\" title\u003d\"Th\u0026iacute;ch\" aria-label\u003d\"Button\"\u003e\u003ci class\u003d\"icon inline-block font-[\u0027bm-font-icon\u0027] not-italic font-normal normal-case leading-none antialiased [speak:never] [font-variant:normal] ic-thumbs-up\"\u003e\u003c/i\u003e\u003c/button\u003e\u003c/span\u003e\n   \u003cspan\u003e\u003cbutton class\u003d\"relative font-normal text-center cursor-pointer normal-case border-0 transition-button disabled:shadow-none disabled:opacity-50 disabled:cursor-not-allowed item-bookmark hover:text-[var(--primary)] btn-social w-[40px] h-[40px] flex items-center justify-center text-[20px] mt-0 mb-[10px] rounded-[50%] bg-[#e9ecef]\" tabindex\u003d\"0\" type\u003d\"button\" title\u003d\"Lưu tin\" aria-label\u003d\"Button\"\u003e\u003ci class\u003d\"icon inline-block font-[\u0027bm-font-icon\u0027] not-italic font-normal normal-case leading-none antialiased [speak:never] [font-variant:normal] ic-bookmark\"\u003e\u003c/i\u003e\u003c/button\u003e\u003c/span\u003e\n   \u003cspan\u003e\u003cbutton class\u003d\"relative font-normal text-center cursor-pointer normal-case border-0 transition-button disabled:shadow-none disabled:opacity-50 disabled:cursor-not-allowed btn-report item-report w-[40px] h-[40px] flex items-center justify-center text-[20px] mt-0 mb-[10px] rounded-[50%] bg-[#e9ecef] hover:text-[var(--primary)]\" tabindex\u003d\"0\" type\u003d\"button\" title\u003d\"B\u0026aacute;o lỗi\" aria-label\u003d\"Button\"\u003e\u003ci class\u003d\"icon inline-block font-[\u0027bm-font-icon\u0027] not-italic font-normal normal-case leading-none antialiased [speak:never] [font-variant:normal] ic-comment-exclamation1\"\u003e\u003c/i\u003e\u003c/button\u003e\u003c/span\u003e\n  \u003c/div\u003e\n \u003c/div\u003e\n\u003c/div\u003e"
}